gizmo_sdk/__init__.py
gizmo_sdk/_base_client.py
gizmo_sdk/_client.py
gizmo_sdk/_compat.py
gizmo_sdk/_constants.py
gizmo_sdk/_exceptions.py
gizmo_sdk/_files.py
gizmo_sdk/_models.py
gizmo_sdk/_qs.py
gizmo_sdk/_resource.py
gizmo_sdk/_response.py
gizmo_sdk/_streaming.py
gizmo_sdk/_types.py
gizmo_sdk/_version.py
gizmo_sdk/py.typed
gizmo_sdk/_utils/__init__.py
gizmo_sdk/_utils/_compat.py
gizmo_sdk/_utils/_datetime_parse.py
gizmo_sdk/_utils/_logs.py
gizmo_sdk/_utils/_proxy.py
gizmo_sdk/_utils/_reflection.py
gizmo_sdk/_utils/_resources_proxy.py
gizmo_sdk/_utils/_streams.py
gizmo_sdk/_utils/_sync.py
gizmo_sdk/_utils/_transform.py
gizmo_sdk/_utils/_typing.py
gizmo_sdk/_utils/_utils.py
gizmo_sdk/lib/.keep
gizmo_sdk/resources/__init__.py
gizmo_sdk/resources/applications.py
gizmo_sdk/types/__init__.py
gizmo_sdk/types/application_create_params.py
gizmo_sdk/types/application_create_response.py
gizmo_sdk/types/application_retrieve_response.py
gizmo_sdk/types/application_update_params.py
gizmo_sdk/types/application_update_response.py
gizmo_sdk/types/loan_purpose.py
gizmo_sdk/types/milestone.py
gizmo_sdk/types/state.py
gizmo_sdk-1.0.0.dist-info/METADATA
gizmo_sdk-1.0.0.dist-info/WHEEL
gizmo_sdk-1.0.0.dist-info/licenses/LICENSE
gizmo_sdk-1.0.0.dist-info/RECORD
